clerk_backend_api/.genignore
clerk_backend_api/__init__.py
clerk_backend_api/_hooks/__init__.py
clerk_backend_api/_hooks/clerk_before_request_hook.py
clerk_backend_api/_hooks/registration.py
clerk_backend_api/_hooks/sdkhooks.py
clerk_backend_api/_hooks/types.py
clerk_backend_api/_version.py
clerk_backend_api/actortokens.py
clerk_backend_api/allowlistidentifiers.py
clerk_backend_api/api_keys.py
clerk_backend_api/basesdk.py
clerk_backend_api/betafeatures.py
clerk_backend_api/billing.py
clerk_backend_api/blocklistidentifiers_sdk.py
clerk_backend_api/clients.py
clerk_backend_api/domains_sdk.py
clerk_backend_api/emailaddresses.py
clerk_backend_api/emailandsmstemplates.py
clerk_backend_api/emailsmstemplates.py
clerk_backend_api/httpclient.py
clerk_backend_api/instancesettings_sdk.py
clerk_backend_api/invitations.py
clerk_backend_api/jwks_sdk.py
clerk_backend_api/jwttemplates.py
clerk_backend_api/m2m.py
clerk_backend_api/machines.py
clerk_backend_api/miscellaneous.py
clerk_backend_api/models/__init__.py
clerk_backend_api/models/actortoken.py
clerk_backend_api/models/adddomainop.py
clerk_backend_api/models/allowlistidentifier.py
clerk_backend_api/models/assignpermissiontoorganizationroleop.py
clerk_backend_api/models/banuserop.py
clerk_backend_api/models/billingpaymentattempt.py
clerk_backend_api/models/billingstatement.py
clerk_backend_api/models/blocklistidentifier.py
clerk_backend_api/models/blocklistidentifiers.py
clerk_backend_api/models/cancelcommercesubscriptionitemop.py
clerk_backend_api/models/changeproductioninstancedomainop.py
clerk_backend_api/models/clerkbaseerror.py
clerk_backend_api/models/clerkerror.py
clerk_backend_api/models/clerkerrors.py
clerk_backend_api/models/client.py
clerk_backend_api/models/cnametarget.py
clerk_backend_api/models/commercemoneyresponse.py
clerk_backend_api/models/commercepayerresponse.py
clerk_backend_api/models/commercepaymentmethodresponse.py
clerk_backend_api/models/commerceplan.py
clerk_backend_api-4.2.0.dist-info/METADATA
clerk_backend_api-4.2.0.dist-info/WHEEL
clerk_backend_api-4.2.0.dist-info/licenses/LICENSE
clerk_backend_api-4.2.0.dist-info/RECORD
