Metadata-Version: 2.4
Name: clerk-backend-api
Version: 4.2.0
Summary: Python Client SDK for clerk.dev
License-File: LICENSE
Author: Clerk
Requires-Python: >=3.9.2
Classifier: Programming Language :: Python :: 3
Classifier: Programming Language :: Python :: 3.10
Classifier: Programming Language :: Python :: 3.11
Classifier: Programming Language :: Python :: 3.12
Classifier: Programming Language :: Python :: 3.13
Classifier: Programming Language :: Python :: 3.14
Requires-Dist: cryptography (>=45.0.0,<46.0.0)
Requires-Dist: httpcore (>=1.0.9)
Requires-Dist: httpx (>=0.28.1)
Requires-Dist: pydantic (>=2.11.2)
Requires-Dist: pyjwt (>=2.9.0,<3.0.0)
Project-URL: Repository, https://github.com/clerk/clerk-sdk-python.git
